ffsuspend.py
ffsuspend-0.1.dist-info/LICENSE.txt
ffsuspend-0.1.dist-info/METADATA
ffsuspend-0.1.dist-info/WHEEL
ffsuspend-0.1.dist-info/entry_points.txt
ffsuspend-0.1.dist-info/top_level.txt
ffsuspend-0.1.dist-info/RECORD
