Metadata-Version: 2.1
Name: ffsuspend
Version: 0.1
Summary: Suspend processes when X window not visible (i3-wm only)
Home-page: https://github.com/tu500/ffsuspend
Author: Philip Matura
Author-email: philip.m@tura-home.de
License: GPLv3+
Platform: UNKNOWN
Classifier: Development Status :: 4 - Beta
Classifier: Programming Language :: Python :: 3
Classifier: Environment :: X11 Applications
Classifier: License :: OSI Approved :: GNU General Public License v3 or later (GPLv3+)
Classifier: Operating System :: POSIX :: Linux
Classifier: Topic :: Desktop Environment :: Window Managers
Classifier: Typing :: Typed
